trade_republic_api/__init__.py
trade_republic_api/__main__.py
trade_republic_api/cli.py
trade_republic_api-0.0.1.dist-info/AUTHORS.rst
trade_republic_api-0.0.1.dist-info/LICENSE
trade_republic_api-0.0.1.dist-info/METADATA
trade_republic_api-0.0.1.dist-info/WHEEL
trade_republic_api-0.0.1.dist-info/entry_points.txt
trade_republic_api-0.0.1.dist-info/top_level.txt
trade_republic_api-0.0.1.dist-info/RECORD
