Metadata-Version: 2.1
Name: trade-republic-api
Version: 0.0.1
Summary: Trade Republic API (Unofficial)
Home-page: https://github.com/unimun/trade-republic-api
Author: Dongbin Han
Author-email: unimunity@gmail.com
License: BSD-2-Clause
Project-URL: Documentation, https://trade-republic-api.readthedocs.io/
Project-URL: Changelog, https://trade-republic-api.readthedocs.io/en/latest/changelog.html
Project-URL: Issue Tracker, https://github.com/unimun/trade-republic-api/issues
Classifier: Development Status :: 5 - Production/Stable
Classifier: Intended Audience :: Developers
Classifier: License :: OSI Approved :: BSD License
Classifier: Operating System :: Unix
Classifier: Operating System :: POSIX
Classifier: Operating System :: Microsoft :: Windows
Classifier: Programming Language :: Python
Classifier: Programming Language :: Python :: 3
Classifier: Programming Language :: Python :: 3 :: Only
Classifier: Programming Language :: Python :: 3.7
Classifier: Programming Language :: Python :: 3.8
Classifier: Programming Language :: Python :: 3.9
Classifier: Programming Language :: Python :: 3.10
Classifier: Programming Language :: Python :: 3.11
Classifier: Programming Language :: Python :: Implementation :: CPython
Classifier: Programming Language :: Python :: Implementation :: PyPy
Classifier: Topic :: Utilities
Requires-Python: >=3.7
License-File: LICENSE
License-File: AUTHORS.rst
Requires-Dist: click
